baseballquery/__init__.py
baseballquery/chadwick_cols.py
baseballquery/convert_mlbam.py
baseballquery/database.py
baseballquery/download.py
baseballquery/eventTypes.json
baseballquery/linear_weights.py
baseballquery/migrations.py
baseballquery/parse_game.py
baseballquery/parse_plate_appearance.py
baseballquery/parse_season.py
baseballquery/retrosheet_cwevent_convert.py
baseballquery/stat_calculator.py
baseballquery/stat_splits.py
baseballquery/update_data.py
baseballquery/utils.py
baseballquery/register/data/countries.csv
baseballquery/register/data/links.csv
baseballquery/register/data/names.csv
baseballquery/register/data/people-0.csv
baseballquery/register/data/people-1.csv
baseballquery/register/data/people-2.csv
baseballquery/register/data/people-3.csv
baseballquery/register/data/people-4.csv
baseballquery/register/data/people-5.csv
baseballquery/register/data/people-6.csv
baseballquery/register/data/people-7.csv
baseballquery/register/data/people-8.csv
baseballquery/register/data/people-9.csv
baseballquery/register/data/people-a.csv
baseballquery/register/data/people-b.csv
baseballquery/register/data/people-c.csv
baseballquery/register/data/people-d.csv
baseballquery/register/data/people-e.csv
baseballquery/register/data/people-f.csv
baseballquery-0.3.14.dist-info/METADATA
baseballquery-0.3.14.dist-info/WHEEL
baseballquery-0.3.14.dist-info/top_level.txt
baseballquery-0.3.14.dist-info/RECORD
