Metadata-Version: 2.4
Name: baseballquery
Version: 0.3.14
Summary: A library to query MLB stats including on a game level
Home-page: https://github.com/jso8910/baseballquery
Author: Jason R
Author-email: mail4jasonr@gmail.com
License: MIT
Keywords: python
Classifier: Development Status :: 4 - Beta
Classifier: Intended Audience :: Developers
Classifier: License :: OSI Approved :: MIT License
Classifier: Natural Language :: English
Classifier: Programming Language :: Python :: 3.12
Requires-Python: >=3.9
Requires-Dist: requests
Requires-Dist: tqdm
Requires-Dist: pandas
Requires-Dist: typing-extensions
Requires-Dist: numpy
Requires-Dist: pyarrow
Requires-Dist: sqlalchemy
Requires-Dist: msgspec
Requires-Dist: aiohttp[speedups]
Dynamic: author
Dynamic: author-email
Dynamic: classifier
Dynamic: description
Dynamic: description-content-type
Dynamic: home-page
Dynamic: keywords
Dynamic: license
Dynamic: requires-dist
Dynamic: requires-python
Dynamic: summary
